[{"snake": [[5, 6], [5, 5]], "food": [5, 2], "score": 0}, {"snake": [[5, 7], [5, 6]], "food": [5, 2], "score": 0}, {"snake": [[6, 7], [5, 7]], "food": [5, 2], "score": 0}, {"snake": [[7, 7], [6, 7]], "food": [5, 2], "score": 0}, {"snake": [[8, 7], [7, 7]], "food": [5, 2], "score": 0}, {"snake": [[9, 7], [8, 7]], "food": [5, 2], "score": 0}, {"snake": [[9, 6], [9, 7]], "food": [5, 2], "score": 0}, {"snake": [[8, 6], [9, 6]], "food": [5, 2], "score": 0}, {"snake": [[7, 6], [8, 6]], "food": [5, 2], "score": 0}, {"snake": [[6, 6], [7, 6]], "food": [5, 2], "score": 0}, {"snake": [[5, 6], [6, 6]], "food": [5, 2], "score": 0}, {"snake": [[4, 6], [5, 6]], "food": [5, 2], "score": 0}, {"snake": [[3, 6], [4, 6]], "food": [5, 2], "score": 0}, {"snake": [[2, 6], [3, 6]], "food": [5, 2], "score": 0}, {"snake": [[1, 6], [2, 6]], "food": [5, 2], "score": 0}, {"snake": [[0, 6], [1, 6]], "food": [5, 2], "score": 0}, {"snake": [[0, 6], [1, 6]], "food": [5, 2], "score": 0}]